Metadata-Version: 2.1
Name: Polthon
Version: 0.0.2
Summary: Python po polsku/Python in polish
Author: Sarkilo
Keywords: polthon,python po polsku,polska,poland,polish
License-File: license.txt
